alibabacloud_abfs20211230/__init__.py
alibabacloud_abfs20211230/client.py
alibabacloud_abfs20211230/models.py
alibabacloud_abfs20211230-3.6.0.dist-info/LICENSE
alibabacloud_abfs20211230-3.6.0.dist-info/METADATA
alibabacloud_abfs20211230-3.6.0.dist-info/WHEEL
alibabacloud_abfs20211230-3.6.0.dist-info/top_level.txt
alibabacloud_abfs20211230-3.6.0.dist-info/RECORD
